{
  "head": {
    "text": "USBInterpacketTimer \u2014 FS reset and delay strobes"
  },
  "signal": [
    {
      "name": "clk",
      "wave": "p......................................................................................................................."
    },
    {
      "name": "\u2192 start",
      "wave": "0....10................................................................................................................."
    },
    {
      "name": "tx_allowed \u2192",
      "wave": "0...............10......................................................................................................"
    },
    {
      "name": "tx_timeout \u2192",
      "wave": "0.....................................10................................................................................"
    },
    {
      "name": "rx_timeout \u2192",
      "wave": "0.....................................................................................10................................"
    }
  ]
}